pycococt/__init__.py
pycococt/cococt.py
pycococt/test.py
pycococt-0.1.dist-info/METADATA
pycococt-0.1.dist-info/WHEEL
pycococt-0.1.dist-info/top_level.txt
pycococt-0.1.dist-info/RECORD
