Metadata-Version: 2.1
Name: pycococt
Version: 0.1
Summary: Python interface to the COCO-CameraTrap datasets.
Home-page: UNKNOWN
License: UNKNOWN
Platform: UNKNOWN
Requires-Dist: pycocotools (>=2.0.0)
